domdf_wxpython_tools/ColourPickerPanel.py
domdf_wxpython_tools/StylePickerPanel.py
domdf_wxpython_tools/WebView.py
domdf_wxpython_tools/__init__.py
domdf_wxpython_tools/border_config.py
domdf_wxpython_tools/chartpanel.py
domdf_wxpython_tools/clearable_textctrl.py
domdf_wxpython_tools/dialogs.py
domdf_wxpython_tools/editable_listbox.py
domdf_wxpython_tools/events.py
domdf_wxpython_tools/filebrowsectrl.py
domdf_wxpython_tools/icons.py
domdf_wxpython_tools/imagepanel.py
domdf_wxpython_tools/keyboard.py
domdf_wxpython_tools/list_dialog.py
domdf_wxpython_tools/logctrl.py
domdf_wxpython_tools/picker.py
domdf_wxpython_tools/projections.py
domdf_wxpython_tools/style_picker.py
domdf_wxpython_tools/tabbable_textctrl.py
domdf_wxpython_tools/textctrlwrapper.py
domdf_wxpython_tools/timer_thread.py
domdf_wxpython_tools/utils.py
domdf_wxpython_tools/validators.py
domdf_wxpython_tools/panel_listctrl/Default.css
domdf_wxpython_tools/panel_listctrl/__init__.py
domdf_wxpython_tools/panel_listctrl/constants.py
domdf_wxpython_tools/panel_listctrl/css_parser.py
domdf_wxpython_tools/panel_listctrl/font_parser.py
domdf_wxpython_tools/panel_listctrl/panel_listctrl.py
domdf_wxpython_tools-0.3.0.post1.dist-info/LICENSE
domdf_wxpython_tools-0.3.0.post1.dist-info/METADATA
domdf_wxpython_tools-0.3.0.post1.dist-info/WHEEL
domdf_wxpython_tools-0.3.0.post1.dist-info/top_level.txt
domdf_wxpython_tools-0.3.0.post1.dist-info/RECORD
