Metadata-Version: 2.1
Name: domdf-wxpython-tools
Version: 0.3.0.post1
Summary: Tools and widgets for wxPython.
Home-page: https://github.com/domdfcoding/domdf_wxpython_tools
Author: Dominic Davis-Foster
Author-email: Dominic Davis-Foster <dominic@davis-foster.co.uk>
License: GNU LESSER GENERAL PUBLIC LICENSE
Project-URL: Homepage, https://github.com/domdfcoding/domdf_wxpython_tools
Project-URL: Issue Tracker, https://github.com/domdfcoding/domdf_wxpython_tools/issues
Project-URL: Source Code, https://github.com/domdfcoding/domdf_wxpython_tools
Project-URL: Documentation, https://domdf-wxpython-tools.readthedocs.io/en/latest
Platform: Windows
Platform: macOS
Platform: Linux
Classifier: Development Status :: 4 - Beta
Classifier: Intended Audience :: Developers
Classifier: License :: OSI Approved :: GNU Lesser General Public License v3 or later (LGPLv3+)
Classifier: Operating System :: OS Independent
Classifier: Programming Language :: Python
Classifier: Programming Language :: Python :: 3 :: Only
Classifier: Programming Language :: Python :: 3.6
Classifier: Programming Language :: Python :: 3.7
Classifier: Programming Language :: Python :: 3.8
Classifier: Programming Language :: Python :: 3.9
Classifier: Programming Language :: Python :: 3.10
Classifier: Programming Language :: Python :: 3.11
Classifier: Programming Language :: Python :: Implementation :: CPython
Classifier: Topic :: Software Development :: Libraries :: Python Modules
Requires-Python: >=3.6.1
License-File: LICENSE
Requires-Dist: cawdrey (>=0.1.5)
Requires-Dist: domdf-python-tools (>=0.9.0)
Requires-Dist: mathematical (>=0.1.7)
Requires-Dist: matplotlib (>=3.0.0)
Requires-Dist: numpy (>=1.16.0)
Requires-Dist: pillow (>=6.2.3)
Requires-Dist: tinycss (>=0.4)
Requires-Dist: typing-extensions (>=3.10.0.0)
Requires-Dist: webcolors (>=1.10)
Requires-Dist: wxpython (>=4.0.7) ; platform_system == "Darwin" and python_version < "3.9"
Requires-Dist: wxpython (>=4.0.7) ; platform_system == "Windows" and python_version < "3.9"
